quickbelog/__init__.py
quickbelog/logger.py
quickbelog-1.1.0.dist-info/METADATA
quickbelog-1.1.0.dist-info/WHEEL
quickbelog-1.1.0.dist-info/top_level.txt
quickbelog-1.1.0.dist-info/RECORD
