Metadata-Version: 2.1
Name: quickbelog
Version: 1.1.0
Summary: Automate IT operations
Home-page: https://github.com/eldad1221/quickbelog
Author: Eldad Bishari
Author-email: eldad@1221tlv.org
License: UNKNOWN
Platform: UNKNOWN
Classifier: Programming Language :: Python :: 3
Classifier: License :: OSI Approved :: MIT License
Classifier: Operating System :: OS Independent
Requires-Python: >=3.6
